teradatasql/__init__.py
teradatasql/__main__.py
teradatasql/py.typed
teradatasql/teradatasql.aix.so
teradatasql/teradatasql.arm.fips.so
teradatasql/teradatasql.arm.so
teradatasql/teradatasql.dll
teradatasql/teradatasql.dylib
teradatasql/teradatasql.fips.so
teradatasql/teradatasql.power.so
teradatasql/teradatasql.so
teradatasql/teradatasql.x86.dll
teradatasql/teradatasql.x86.so
teradatasql/vernumber.py
teradatasql-20.0.0.49.data/data/teradatasql/LICENSE
teradatasql-20.0.0.49.data/data/teradatasql/README.md
teradatasql-20.0.0.49.data/data/teradatasql/THIRDPARTYLICENSE
teradatasql-20.0.0.49.data/data/teradatasql/samples/AGKRBatchInsert.py
teradatasql-20.0.0.49.data/data/teradatasql/samples/AGKRInsertSelect.py
teradatasql-20.0.0.49.data/data/teradatasql/samples/AbortSession.py
teradatasql-20.0.0.49.data/data/teradatasql/samples/BatchInsPerf.py
teradatasql-20.0.0.49.data/data/teradatasql/samples/BatchInsert.py
teradatasql-20.0.0.49.data/data/teradatasql/samples/BatchInsertCSV.py
teradatasql-20.0.0.49.data/data/teradatasql/samples/CancelSleep.py
teradatasql-20.0.0.49.data/data/teradatasql/samples/CharPadding.py
teradatasql-20.0.0.49.data/data/teradatasql/samples/CommitRollback.py
teradatasql-20.0.0.49.data/data/teradatasql/samples/DecimalDigits.py
teradatasql-20.0.0.49.data/data/teradatasql/samples/DriverDatabaseVersion.py
teradatasql-20.0.0.49.data/data/teradatasql/samples/ElicitFile.py
teradatasql-20.0.0.49.data/data/teradatasql/samples/ExportCSVResult.py
teradatasql-20.0.0.49.data/data/teradatasql/samples/ExportCSVResults.py
teradatasql-20.0.0.49.data/data/teradatasql/samples/FakeExportCSVResults.py
teradatasql-20.0.0.49.data/data/teradatasql/samples/FakeResultSetCon.py
teradatasql-20.0.0.49.data/data/teradatasql/samples/FakeResultSetEsc.py
teradatasql-20.0.0.49.data/data/teradatasql/samples/FastExportCSV.py
teradatasql-20.0.0.49.data/data/teradatasql/samples/FastExportTable.py
teradatasql-20.0.0.49.dist-info/METADATA
teradatasql-20.0.0.49.dist-info/RECORD
teradatasql-20.0.0.49.dist-info/WHEEL
teradatasql-20.0.0.49.dist-info/top_level.txt
